LICENSE.txt
evo_package_openai/__init__.py
evo_package_openai/automation/api.yaml
evo_package_openai/automation/entity.yaml
evo_package_openai/control/COpenaiApi.py
evo_package_openai/control/__init__.py
evo_package_openai/entity/EOpenaiInfo.py
evo_package_openai/entity/__init__.py
evo_package_openai/utility/IuOpenai.py
evo_package_openai/utility/UOpenaiApi.py
evo_package_openai/utility/__init__.py
evo_package_openai-2024.10.22327.dist-info/LICENSE.txt
evo_package_openai-2024.10.22327.dist-info/METADATA
evo_package_openai-2024.10.22327.dist-info/WHEEL
evo_package_openai-2024.10.22327.dist-info/RECORD
