Metadata-Version: 2.1
Name: evo-package-openai
Version: 2024.10.22327
Summary: evo-package-openai python
License: CC BY-NC-ND 4.0
Author: cyborg-ai-git
Author-email: 129898917+cyborg-ai-git@users.noreply.github.com
Requires-Python: >=3.10,<4.0
Classifier: License :: Other/Proprietary License
Classifier: Programming Language :: Python :: 3
Classifier: Programming Language :: Python :: 3.10
Classifier: Programming Language :: Python :: 3.11
Classifier: Programming Language :: Python :: 3.12
Requires-Dist: evo-framework
Requires-Dist: evo-package-assistant
Requires-Dist: evo-package-chat
Requires-Dist: openai (>=1.34.0,<2.0.0)
